kekmonitors/__init__.py
kekmonitors/app.py
kekmonitors/base_common.py
kekmonitors/base_monitor.py
kekmonitors/base_scraper.py
kekmonitors/config.py
kekmonitors/discord_embeds.py
kekmonitors/exceptions.py
kekmonitors/monitor_manager.py
kekmonitors/monitor_manager_cli.py
kekmonitors/shoe_manager.py
kekmonitors/shoe_stuff.py
kekmonitors/webhook_manager.py
kekmonitors/comms/__init__.py
kekmonitors/comms/msg.py
kekmonitors/comms/server.py
kekmonitors/utils/__init__.py
kekmonitors/utils/list_db.py
kekmonitors/utils/network_utils.py
kekmonitors/utils/reset_db.py
kekmonitors/utils/stop_moman.py
kekmonitors/utils/tools.py
kekmonitors-0.2.2.dist-info/METADATA
kekmonitors-0.2.2.dist-info/WHEEL
kekmonitors-0.2.2.dist-info/top_level.txt
kekmonitors-0.2.2.dist-info/RECORD
