Metadata-Version: 2.1
Name: kekmonitors
Version: 0.2.2
Summary: Open source codebase for development of sneakers monitors
Home-page: https://github.com/berton7/kekmonitors
Author: berton7
Author-email: francy.berton99@gmail.com
License: UNKNOWN
Platform: UNKNOWN
Classifier: Programming Language :: Python :: 3
Classifier: License :: OSI Approved :: MIT License
Classifier: Operating System :: POSIX
Requires-Python: >=3.6
Requires-Dist: discord.py
Requires-Dist: tornado
Requires-Dist: requests
Requires-Dist: pycurl
Requires-Dist: watchdog
Requires-Dist: pymongo
Requires-Dist: aiohttp[speedups]
Requires-Dist: uvloop ; python_version > "3.6"
